<?xml version="1.0" encoding="UTF-8" standalone="yes"?><sentenceset><sentence><field><fieldtype>WORD</fieldtype><value>methods</value><total>1</total></field><field><fieldtype>WORD</fieldtype><value>to</value><total>1</total></field><field><fieldtype>WORD</fieldtype><value>These</value><total>1</total></field><field><fieldtype>WORD</fieldtype><value>second</value><total>1</total></field><field><fieldtype>WORD</fieldtype><value>both</value><total>1</total></field><field><fieldtype>WORD</fieldtype><value>proven</value><total>1</total></field><field><fieldtype>WORD</fieldtype><value>for</value><total>1</total></field><field><fieldtype>WORD</fieldtype><value>However</value><total>1</total></field><field><fieldtype>WORD</fieldtype><value>good</value><total>1</total></field><field><fieldtype>WORD</fieldtype><value>preferably</value><total>1</total></field><field><fieldtype>WORD</fieldtype><value>optimality</value><total>1</total></field><field><fieldtype>WORD</fieldtype><value>zero</value><total>1</total></field><field><fieldtype>WORD</fieldtype><value>has</value><total>1</total></field><field><fieldtype>WORD</fieldtype><value>seeks</value><total>1</total></field><field><fieldtype>WORD</fieldtype><value>function</value><total>1</total></field><field><fieldtype>WORD</fieldtype><value>of</value><total>1</total></field><field><fieldtype>WORD</fieldtype><value>are</value><total>1</total></field><field><fieldtype>WORD</fieldtype><value>quadratic</value><total>1</total></field><field><fieldtype>WORD</fieldtype><value>Newtons</value><total>1</total></field><field><fieldtype>WORD</fieldtype><value>be</value><total>1</total></field><field><fieldtype>WORD</fieldtype><value>problems</value><total>1</total></field><field><fieldtype>WORD</fieldtype><value>such</value><total>1</total></field><field><fieldtype>WORD</fieldtype><value>condition</value><total>1</total></field><field><fieldtype>WORD</fieldtype><value>class</value><total>1</total></field><field><fieldtype>WORD</fieldtype><value>optimization</value><total>1</total></field><field><fieldtype>WORD</fieldtype><value>guaranteed</value><total>1</total></field><field><fieldtype>WORD</fieldtype><value>and</value><total>1</total></field><field><fieldtype>WORD</fieldtype><value>differentiable</value><total>1</total></field><field><fieldtype>WORD</fieldtype><value>not</value><total>1</total></field><field><fieldtype>WORD</fieldtype><value>that</value><total>1</total></field><field><fieldtype>WORD</fieldtype><value>stationary</value><total>1</total></field><field><fieldtype>WORD</fieldtype><value>near</value><total>1</total></field><field><fieldtype>WORD</fieldtype><value>even</value><total>1</total></field><field><fieldtype>WORD</fieldtype><value>unconstrained</value><total>1</total></field><field><fieldtype>WORD</fieldtype><value>converge</value><total>1</total></field><field><fieldtype>WORD</fieldtype><value>expansion</value><total>1</total></field><field><fieldtype>WORD</fieldtype><value>optimum</value><total>1</total></field><field><fieldtype>WORD</fieldtype><value>have</value><total>1</total></field><field><fieldtype>WORD</fieldtype><value>use</value><total>1</total></field><field><fieldtype>WORD</fieldtype><value>techniques</value><total>1</total></field><field><fieldtype>WORD</fieldtype><value>derivatives</value><total>1</total></field><field><fieldtype>WORD</fieldtype><value>algorithm</value><total>1</total></field><field><fieldtype>WORD</fieldtype><value>The</value><total>1</total></field><field><fieldtype>WORD</fieldtype><value>continuously</value><total>1</total></field><field><fieldtype>WORD</fieldtype><value>twice</value><total>1</total></field><field><fieldtype>WORD</fieldtype><value>unless</value><total>1</total></field><field><fieldtype>WORD</fieldtype><value>performance</value><total>1</total></field><field><fieldtype>WORD</fieldtype><value>For</value><total>1</total></field><field><fieldtype>WORD</fieldtype><value>optimizations</value><total>1</total></field><field><fieldtype>WORD</fieldtype><value>BroydenFletcherGoldfarbShanno</value><total>1</total></field><field><fieldtype>WORD</fieldtype><value>Taylor</value><total>1</total></field><field><fieldtype>WORD</fieldtype><value>is</value><total>1</total></field><field><fieldtype>WORD</fieldtype><value>a</value><total>1</total></field><field><fieldtype>WORD</fieldtype><value>iterative</value><total>1</total></field><field><fieldtype>WORD</fieldtype><value>the</value><total>1</total></field><field><fieldtype>WORD</fieldtype><value>solving</value><total>1</total></field><field><fieldtype>WORD</fieldtype><value>approximates</value><total>1</total></field><field><fieldtype>WORD</fieldtype><value>point</value><total>1</total></field><field><fieldtype>WORD</fieldtype><value>an</value><total>1</total></field><field><fieldtype>WORD</fieldtype><value>method</value><total>1</total></field><field><fieldtype>WORD</fieldtype><value>necessary</value><total>1</total></field><field><fieldtype>WORD</fieldtype><value>nonsmooth</value><total>1</total></field><field><fieldtype>WORD</fieldtype><value>first</value><total>1</total></field><field><fieldtype>WORD</fieldtype><value>hillclimbing</value><total>1</total></field><field><fieldtype>WORD</fieldtype><value>BFGS</value><total>1</total></field><field><fieldtype>WORD</fieldtype><value>nonlinear</value><total>1</total></field><field><fieldtype>WORD</fieldtype><value>gradient</value><total>1</total></field><field><fieldtype>PUNCTUATION</fieldtype><value>–</value><total>1</total></field><field><fieldtype>PUNCTUATION</fieldtype><value>'</value><total>1</total></field><field><fieldtype>PUNCTUATION</fieldtype><value>(</value><total>1</total></field><field><fieldtype>PUNCTUATION</fieldtype><value>)</value><total>1</total></field><field><fieldtype>PUNCTUATION</fieldtype><value>.</value><total>1</total></field><field><fieldtype>PUNCTUATION</fieldtype><value>,</value><total>1</total></field><field><fieldtype>PUNCTUATION</fieldtype><value>-</value><total>1</total></field><field><fieldtype>WHITESPACE</fieldtype><total>98</total></field><field><fieldtype>NAMED_ENTITY</fieldtype><value>Broyden–Fletcher–Goldfarb–Shanno</value><start_index>4</start_index><end_index>36</end_index></field><field><fieldtype>NAMED_ENTITY</fieldtype><value>Newton</value><start_index>165</start_index><end_index>171</end_index></field><field><fieldtype>NAMED_ENTITY</fieldtype><value>Newton</value><start_index>409</start_index><end_index>415</end_index></field><field><fieldtype>NAMED_ENTITY</fieldtype><value>BFGS</value><start_index>38</start_index><end_index>42</end_index></field><field><fieldtype>NAMED_ENTITY</fieldtype><value>BFGS</value><start_index>140</start_index><end_index>144</end_index></field><field><fieldtype>NAMED_ENTITY</fieldtype><value>BFGS</value><start_index>433</start_index><end_index>437</end_index></field><field><fieldtype>NAMED_ENTITY</fieldtype><value>BFGS</value><start_index>629</start_index><end_index>633</end_index></field></sentence></sentenceset>